LICENSE
MANIFEST.in
README.md
setup.json
setup.py
aiida_QECpWorkChain/__init__.py
aiida_QECpWorkChain/cpConvergence.py
aiida_QECpWorkChain/generate_concatenate.py
aiida_QECpWorkChain/utils.py
aiida_QECpWorkChain/workflow.py
aiida_QECpWorkChain/write_cp_traj.py
aiida_QECpWorkChain.egg-info/PKG-INFO
aiida_QECpWorkChain.egg-info/SOURCES.txt
aiida_QECpWorkChain.egg-info/dependency_links.txt
aiida_QECpWorkChain.egg-info/entry_points.txt
aiida_QECpWorkChain.egg-info/requires.txt
aiida_QECpWorkChain.egg-info/top_level.txt