Metadata-Version: 2.1
Name: aiida-QECpWorkChain
Version: 0.2.0a0
Summary: Car-Parrinello Work Chain with Quantum Espresso. This workchain does a full CP simulation, from the choice of the electronic mass and the timestep, to the choice of the best parallelization options, and then it does the NPT equilibration and a final NVE simulation at the prescribed P and T. Automates as much as possible.
Home-page: https://github.com/rikigigi/aiida-QECpWorkChain
Author: Riccardo Bertossa
Author-email: rbertoss@sissa.it
License: GPLv3
Classifier: Programming Language :: Python
Classifier: Intended Audience :: Science/Research
Classifier: License :: OSI Approved :: GNU General Public License v3 (GPLv3)
Classifier: Natural Language :: English
Classifier: Framework :: AiiDA
License-File: LICENSE
